robustress/__init__.py
robustress/rank.py
robustress/sortedness.py
robustress-0.220716.1.dist-info/LICENSE
robustress-0.220716.1.dist-info/WHEEL
robustress-0.220716.1.dist-info/METADATA
robustress-0.220716.1.dist-info/RECORD
