Metadata-Version: 2.1
Name: robustress
Version: 0.220716.1
Summary: 
Author: davips
Author-email: dpsabc@gmail.com
Requires-Python: >=3.8,<3.10
Classifier: Programming Language :: Python :: 3
Classifier: Programming Language :: Python :: 3.8
Classifier: Programming Language :: Python :: 3.9
Requires-Dist: PyQt5 (>=5.15.7,<6.0.0)
Requires-Dist: lange (>=0.2101.24,<0.2102.0)
Requires-Dist: matplotlib (>=3.5.2,<4.0.0)
Requires-Dist: numpy (>=1.22.0,<1.23.0)
Requires-Dist: scipy (>=1.8.1,<2.0.0)
Requires-Dist: sympy (>=1.10.1,<2.0.0)
